{
  "author": [
    {
      "tag": "@aRiveraMerida",
      "link": "https://www.linkedin.com/in/albertoriveramerida/"
    },
    {
      "tag": "@Ccastillo06",
      "link": "https://www.linkedin.com/in/cristiancastillonavarro/"
    }
  ],
  "cover": "https://res.cloudinary.com/db38x6luj/image/upload/v1644260534/posts/react.png",
  "description": "Creamos nuestra primera app usando la API de Rick & Morty",
  "title": "React desde 0 | Conceptos base - Rick & Morty App",
  "date": "02/07/2022 20:05:00",
  "tags": ["react"]
}
