{
  "author": [
    {
      "tag": "@aRiveraMerida",
      "link": "https://www.linkedin.com/in/albertoriveramerida/"
    },
    {
      "tag": "@Ccastillo06",
      "link": "https://www.linkedin.com/in/cristiancastillonavarro/"
    }
  ],
  "cover": "https://res.cloudinary.com/db38x6luj/image/upload/v1644260534/posts/react.png",
  "description": "Veremos como crear Custom Hooks y tendremos varios ejemplos",
  "title": "React desde 0 | Hooks [Custom Hooks]",
  "date": "02/23/2022 12:00:00",
  "tags": ["react"]
}
